__init__.py
setup.py
openvi/__init__.py
openvi/auto_trainer.py
openvi/deployment.py
openvi/global_data.py
openvi/main.py
openvi/main_pi.py
openvi/model_table.py
openvi/utils.py
openvi/__pycache__/__init__.cpython-310.pyc
openvi/__pycache__/__init__.cpython-39.pyc
openvi/__pycache__/auto_trainer.cpython-39.pyc
openvi/__pycache__/deployment.cpython-39.pyc
openvi/__pycache__/global_data.cpython-39.pyc
openvi/__pycache__/main.cpython-310.pyc
openvi/__pycache__/main.cpython-39.pyc
openvi/__pycache__/model_table.cpython-39.pyc
openvi/__pycache__/utils.cpython-39.pyc
openvi/font/Roboto/LICENSE.txt
openvi/font/Roboto/Roboto-Regular.ttf
openvi/node/__init__.py
openvi/node/node_abc.py
openvi/node/__pycache__/__init__.cpython-39.pyc
openvi/node/__pycache__/node_abc.cpython-39.pyc
openvi/node/analysis_node/__init__.py
openvi/node/analysis_node/node_BRISQUE.py
openvi/node/analysis_node/node_fps.py
openvi/node/analysis_node/node_rgb_histgram.py
openvi/node/analysis_node/BRISQUE/brisque_model_live.yml
openvi/node/analysis_node/BRISQUE/brisque_range_live.yml
openvi/node/analysis_node/__pycache__/__init__.cpython-39.pyc
openvi/node/analysis_node/__pycache__/node_BRISQUE.cpython-39.pyc
openvi/node/analysis_node/__pycache__/node_fps.cpython-39.pyc
openvi/node/analysis_node/__pycache__/node_rgb_histgram.cpython-39.pyc
openvi/node/deep_learning_node/__init__.py
openvi/node/deep_learning_node/node_classification.py
openvi/node/deep_learning_node/node_object_detection.py
openvi/node/deep_learning_node/node_qrcode_detection.py
openvi/node/deep_learning_node/__pycache__/__init__.cpython-39.pyc
openvi/node/deep_learning_node/__pycache__/node_classification.cpython-39.pyc
openvi/node/deep_learning_node/__pycache__/node_object_detection.cpython-39.pyc
openvi/node/deep_learning_node/__pycache__/node_qrcode_detection.cpython-39.pyc
openvi/node/deep_learning_node/classification/README.md
openvi/node/deep_learning_node/classification/__init__.py
openvi-0.0.3.dist-info/METADATA
openvi-0.0.3.dist-info/WHEEL
openvi-0.0.3.dist-info/entry_points.txt
openvi-0.0.3.dist-info/top_level.txt
openvi-0.0.3.dist-info/RECORD
