Metadata-Version: 2.1
Name: openvi
Version: 0.0.3
Summary: No-code platform for computer vision
Home-page: https://github.com/openvi-team/openvi
Author: OpenVI Team
License: Apache-2.0 license
Keywords: opencv,deep learning,machine learning,computer vision,image processing,video processing,video analysis,video analytics,video
Classifier: License :: OSI Approved :: Apache Software License
Classifier: Programming Language :: Python :: 3.9
Requires-Python: >=3.7
Requires-Dist: numpy >=1.23.0
Requires-Dist: Cython ==0.29.30
Requires-Dist: opencv-contrib-python ==4.5.5.64
Requires-Dist: onnxruntime ==1.16.3
Requires-Dist: dearpygui ==1.6.2
Requires-Dist: mediapipe ==0.10.3
Requires-Dist: protobuf ==3.20.0
Requires-Dist: filterpy ==1.4.5
Requires-Dist: lap ==0.4.0
Requires-Dist: cython-bbox ==0.1.3
Requires-Dist: rich ==12.4.4
Requires-Dist: packaging ==21.3
Requires-Dist: sympy ==1.8
Requires-Dist: dearpygui-ext ==0.9.5
